baumdiff/__init__.py
baumdiff/matcher.py
baumdiff/script.py
baumdiff/shadow.py
baumdiff/simpletree.py
baumdiff/treeaccess.py
baumdiff/treediff.py
baumdiff/treemerge.py
baumdiff-0.2.1.dist-info/LICENSE
baumdiff-0.2.1.dist-info/METADATA
baumdiff-0.2.1.dist-info/WHEEL
baumdiff-0.2.1.dist-info/top_level.txt
baumdiff-0.2.1.dist-info/RECORD
